pubfin/__init__.py
pubfin-1.0.0.dist-info/METADATA
pubfin-1.0.0.dist-info/WHEEL
pubfin-1.0.0.dist-info/RECORD
