Metadata-Version: 2.1
Name: pubfin
Version: 1.0.0
Summary: Reads publically reported financial data via the SEC EDGAR API, and saves to a Findata object with dataframe output functionality.
License: MIT
Author: OHM
Author-email: energydevohm@gmail.com
Requires-Python: >=3.8
Classifier: License :: OSI Approved :: MIT License
Classifier: Programming Language :: Python :: 3
Classifier: Programming Language :: Python :: 3.8
Classifier: Programming Language :: Python :: 3.9
Classifier: Programming Language :: Python :: 3.10
Classifier: Programming Language :: Python :: 3.11
Requires-Dist: pandas (>=2.0)
Requires-Dist: universal-pathlib (>=0.1)
